my_telegram/__init__.py
my_telegram/main.py
my_telegram-0.1.0b1.dist-info/LICENSE
my_telegram-0.1.0b1.dist-info/METADATA
my_telegram-0.1.0b1.dist-info/WHEEL
my_telegram-0.1.0b1.dist-info/RECORD
