Metadata-Version: 2.1
Name: my-telegram
Version: 0.1.0b1
Summary: Python wrapper for my.telegram.org
License: MIT
Author: RuslanUC
Author-email: dev_ruslan_uc@protonmail.com
Requires-Python: >=3.9,<4.0
Classifier: License :: OSI Approved :: MIT License
Classifier: Programming Language :: Python :: 3
Classifier: Programming Language :: Python :: 3.9
Classifier: Programming Language :: Python :: 3.10
Classifier: Programming Language :: Python :: 3.11
Classifier: Programming Language :: Python :: 3.12
Requires-Dist: httpx (>=0.28.1,<0.29.0)
